{
  "title": {
    "en": "ML Web Application with Flask",
    "es": "Aplicacion web de ML con Flask"
  },
  "description": {
    "en": "Iris species classifier trained with scikit-learn and deployed through a Flask web interface prepared for Render.",
    "es": "Clasificador de especies Iris entrenado con scikit-learn e integrado en una interfaz web Flask preparada para Render."
  },
  "repository": "https://github.com/4GeeksAcademy/Tutorial-de-una-aplicaci-n-web-de-ML-con-Flask-Dragcessa1998",
  "preview": "reports/figures/app_banner.png",
  "projectType": "project",
  "difficulty": "beginner",
  "technologies": ["Python", "Flask", "Machine-Learning", "Render", "scikit-learn"]
}
